packs_grpc/__init__.py
packs_grpc/v1/__init__.py
packs_grpc/v1/packs_grpc_pb2.py
packs_grpc/v1/packs_grpc_pb2_grpc.py
packs_grpc-0.1.4.dist-info/METADATA
packs_grpc-0.1.4.dist-info/WHEEL
packs_grpc-0.1.4.dist-info/top_level.txt
packs_grpc-0.1.4.dist-info/RECORD
