Metadata-Version: 2.4
Name: packs-grpc
Version: 0.1.4
Summary: Add your description here
Requires-Python: >=3.12
Requires-Dist: grpcio>=1.76.0
Requires-Dist: grpcio-tools>=1.76.0
